odoo/addons/fieldservice_activity/README.rst
odoo/addons/fieldservice_activity/__init__.py
odoo/addons/fieldservice_activity/__manifest__.py
odoo/addons/fieldservice_activity/i18n/es.po
odoo/addons/fieldservice_activity/i18n/es_AR.po
odoo/addons/fieldservice_activity/i18n/es_CL.po
odoo/addons/fieldservice_activity/i18n/fieldservice_activity.pot
odoo/addons/fieldservice_activity/i18n/it.po
odoo/addons/fieldservice_activity/i18n/pl.po
odoo/addons/fieldservice_activity/i18n/pt_BR.po
odoo/addons/fieldservice_activity/i18n/pt_PT.po
odoo/addons/fieldservice_activity/i18n/sv.po
odoo/addons/fieldservice_activity/models/__init__.py
odoo/addons/fieldservice_activity/models/fsm_activity.py
odoo/addons/fieldservice_activity/models/fsm_order.py
odoo/addons/fieldservice_activity/models/fsm_template.py
odoo/addons/fieldservice_activity/readme/CONFIGURE.md
odoo/addons/fieldservice_activity/readme/CONTRIBUTORS.md
odoo/addons/fieldservice_activity/readme/CREDITS.md
odoo/addons/fieldservice_activity/readme/DESCRIPTION.md
odoo/addons/fieldservice_activity/readme/USAGE.md
odoo/addons/fieldservice_activity/security/ir.model.access.csv
odoo/addons/fieldservice_activity/static/description/field_service_settings_manage_templates.png
odoo/addons/fieldservice_activity/static/description/field_service_template.png
odoo/addons/fieldservice_activity/static/description/field_service_template_activities.png
odoo/addons/fieldservice_activity/static/description/fsm_order_activity_tab.png
odoo/addons/fieldservice_activity/static/description/icon.png
odoo/addons/fieldservice_activity/static/description/icon.svg
odoo/addons/fieldservice_activity/static/description/index.html
odoo/addons/fieldservice_activity/tests/__init__.py
odoo/addons/fieldservice_activity/tests/test_fsm_activity.py
odoo/addons/fieldservice_activity/views/fsm_order.xml
odoo/addons/fieldservice_activity/views/fsm_template.xml
odoo_addon_fieldservice_activity-18.0.1.0.0.7.dist-info/METADATA
odoo_addon_fieldservice_activity-18.0.1.0.0.7.dist-info/WHEEL
odoo_addon_fieldservice_activity-18.0.1.0.0.7.dist-info/top_level.txt
odoo_addon_fieldservice_activity-18.0.1.0.0.7.dist-info/RECORD
